wagtailutils/__init__.py
wagtailutils/admin.py
wagtailutils/apps.py
wagtailutils/blocks.py
wagtailutils/fields.py
wagtailutils/models.py
wagtailutils/serializers.py
wagtailutils/tests.py
wagtailutils/urls.py
wagtailutils/utils.py
wagtailutils/views.py
wagtailutils/migrations/0001_initial.py
wagtailutils/migrations/__init__.py
wagtailutils/static/wagtailutils/css/collapsable_struct.css
wagtailutils/static/wagtailutils/css/tabbed_struct.css
wagtailutils/static/wagtailutils/js/collapsable_struct.js
wagtailutils/static/wagtailutils/js/tabbed_struct.js
wagtailutils-0.0.34.dist-info/METADATA
wagtailutils-0.0.34.dist-info/WHEEL
wagtailutils-0.0.34.dist-info/top_level.txt
wagtailutils-0.0.34.dist-info/RECORD
