Metadata-Version: 2.1
Name: wagtailutils
Version: 0.0.34
Summary: A Wagtail Utility Package
Home-page: UNKNOWN
Author: Amir Mubarak, Nayan Biswas, Utsob Roy
Author-email: amir@co.design, nayan@co.design, roy@co.design
License: UNKNOWN
Platform: UNKNOWN
Classifier: Programming Language :: Python :: 3
Classifier: License :: OSI Approved :: MIT License
Classifier: Operating System :: OS Independent
Requires-Python: >=3.6
Requires-Dist: wagtailmenus
Requires-Dist: djangorestframework
Requires-Dist: django-json-widget
